{"cameraMode":{"drawMode":0,"name":"Shaded","section":"Shading Mode"},"sceneLighting":false,"audioPlay":false,"sceneViewState":{"showFog":true,"showMaterialUpdate":false,"showSkybox":false,"showFlares":true,"showImageEffects":true,"showParticleSystems":true,"showVisualEffectGraphs":true,"m_FxEnabled":true},"in2DMode":false,"pivot":{"x":443.82000732421877,"y":54.743343353271487,"z":340.0404052734375},"rotation":{"x":-0.21337099373340608,"y":-0.6216733455657959,"z":0.1813317835330963,"w":-0.7315157651901245},"size":2.412715196609497,"orthographic":false}